Workbook
Name Authority_Name: #REF!

Sheet Cover
D45: This document contains information licensed under the
F46: Open Government Licence – Alberta

Sheet Tb 1 Total Revenue
A1: Total Revenue
A2: (millions of dollars)
B3: 2023-24 | C3: 2024-25 | E3: 2025-26 | F3: 2026-27 | G3: 2027-28
B4: Actual | C4: Budget | D4: Forecast | E4: Estimate | F4: Target | G4: Target
A5: Personal income tax | B5: 15160 | C5: 15604 | D5: 16119.993 | E5: 15509.644 | F5: 16270.87 | G5: 16980.97
A6: Corporate income tax | B6: 7044.1 | C6: 7028 | D6: 7350.649 | E6: 6764.266 | F6: 6938.231 | G6: 7253.56
A7: Other tax revenue | B7: 4542.7 | C7: 6013.418 | D7: 5994.941 | E7: 6563.361 | F7: 6941.478 | G7: 7155.784
A8: Resource revenue – bitumen | B8: 14517.6 | C8: 12538 | D8: 16859.334 | E8: 12830.42 | F8: 13137.823 | G8: 13498.546
A9: Resource revenue – other | B9: 4769.1 | C9: 4777 | D9: 4649.768 | E9: 4236.886 | F9: 4482.107 | G9: 4316.503
A10: Federal transfers | B10: 12335.9 | C10: 12639.721 | D10: 12958.239 | E10: 13287.499 | F10: 13752.596 | G10: 14228.073
A11: Investment income | B11: 4581.1 | C11: 3266.756 | D11: 5171.461 | E11: 2882.092 | F11: 3134.846 | G11: 3467.248
A12: Net income from bus. enterprises | B12: 1236.7 | C12: 2122.917 | D12: 2064.382 | E12: 2015.736 | F12: 2505.819 | G12: 2567.511
A13: Premiums, fees and licences | B13: 5564.9 | C13: 5383.453 | D13: 5564.771 | E13: 5635.74 | F13: 5873.527 | G13: 6031.889
A14: Other revenue | B14: 4979.2 | C14: 4164.067 | D14: 3958.031 | E14: 4412.137 | F14: 4352.801 | G14: 4469.241
A15: Total Revenue | B15: 74732.3 | C15: 73537.332 | D15: 80691.569 | E15: 74137.781 | F15: 77390.098 | G15: 79969.325

Sheet Tb 2 O&G prices
A1: Oil and Natural Gas Prices
E5: WTI (US$/barrel) – left axis | F5: WCS (US$/barrel) – left axis | G5: ARP (CDN$/GJ) – right axis
D6: 2007-08 | E6: 82.25 | F6: 57.5803 | G6: 5.92
D7: 2008-09 | E7: 85.94 | F7: 66.62656 | G7: 6.97
D8: 2009-10 | E8: 70.71 | F8: 60.72752 | G8: 3.58
D9: 2010-11 | E9: 83.38 | F9: 65.6328 | G9: 3.28
D10: 2011-12 | E10: 97.33 | F10: 81.28504 | G10: 2.98
D11: 2012-13 | E11: 92.07 | F11: 68.41152 | G11: 2.28
D12: 2013-14 | E12: 99.05 | F12: 76.1045 | G12: 3.28
D13: 2014-15 | E13: 80.48 | F13: 62.2864 | G13: 3.51
D14: 2015-16 | E14: 45 | F14: 31.2579 | G14: 2.21
D15: 2016-17 | E15: 47.93 | F15: 34.03854 | G15: 2.01
D16: 2017-18 | E16: 53.69 | F16: 39.2964 | G16: 1.82
D17: 2018-19 | E17: 62.77 | F17: 39.40895 | G17: 1.34
... D26: 2027-28f | E26: 71.5 | F26: 55.9404 | G26: 2.9

Sheet Tb 3 Oil & Gas assumptions
A1: Oil and Natural Gas Assumptions
B3: 2023-24 | C3: 2024-25 | E3: 2025-26 | F3: 2026-27 | G3: 2027-28
B4: Actual | C4: Budget | D4: Forecast | E4: Estimate | F4: Target | G4: Target
A6: Revenue (millions of dollars)
A7: Bitumen royalty | B7: 14517.6 | C7: 12538 | D7: 16859.334 | E7: 12830.42 | F7: 13137.823 | G7: 13498.546
A8: Crude oil royalty | B8: 2971.5 | C8: 2779 | D8: 2945.68 | E8: 2509.523 | F8: 2530.35 | G8: 2695.045
A9: Natural gas / by-products royalties | B9: 1057.5 | C9: 1468 | D9: 1161.232 | E9: 1228.2 | F9: 1434.312 | G9: 1093.111
A10: Prices
A11: West Texas Intermediate (US$/bbl) | B11: 77.83 | C11: 74 | D11: 74 | E11: 68 | F11: 71 | G11: 71.5
A12: Differential (US$/bbl) | B12: 17.29 | C12: 16 | D12: 13.2 | E12: 17.1 | F12: 16.5 | G12: 15.6
A13: WCS @ Hardisty (Cdn$/bbl) | B13: 81.67 | C13: 76.8 | D13: 84.7 | E13: 73.1 | F13: 75.8 | G13: 75.8
A14: Ab. Reference Price (Cdn$/GJ) | B14: 2.07 | C14: 2.9 | D14: 1.2 | E14: 2.5 | F14: 3.1 | G14: 2.9
A15: Production (thousands of barrels / day)
A16: Conventional | B16: 511 | C16: 507 | D16: 528 | E16: 519 | F16: 512 | G16: 504
A17: Raw bitumen | B17: 3332 | C17: 3429 | D17: 3455 | E17: 3558 | F17: 36889 | G17: 3752
A18: Natural gas (billion cubic feet / yr) | B18: 4267 | C18: 4291 | D18: 4304 | E18: 4354 | F18: 4354 | G18: 4354
A19: Exchange rate
A20: (US¢/Cdn$) | B20: 74.2 | C20: 75.9 | D20: 71.7 | E20: 69.63 | F20: 71.9 | G20: 73.8
E21: 5

Sheet Tb 4 NRR
A1: Non-Renewable Resource Revenue
A2: (millions of dollars)
B3: 2023-24 | C3: 2024-25 | E3: 2025-26 | F3: 2026-27 | G3: 2027-28
B4: Actual | C4: Budget | D4: Forecast | E4: Estimate | F4: Target | G4: Target
A6: Bitumen royalty | B6: 14517.6 | C6: 12538 | D6: 16859.334 | E6: 12830.42 | F6: 13137.823 | G6: 13498.546
A7: Crude oil royalty | B7: 2971.5 | C7: 2779 | D7: 2945.68 | E7: 2509.523 | F7: 2530.35 | G7: 2695.045
A8: Natural gas & by-products royalty | B8: 1057.5 | C8: 1468 | D8: 1161.232 | E8: 1228.2 | F8: 1434.312 | G8: 1093.111
A9: Bonuses & sales of Crown leases | B9: 498.5 | C9: 321 | D9: 382.139 | E9: 361.127 | F9: 380.259 | G9: 392.397
A10: Rentals and fees / coal royalty | B10: 241.6 | C10: 209 | D10: 160.717 | E10: 138.036 | F10: 137.186 | G10: 135.95
A11: Total Resource Revenue | B11: 19286.7 | C11: 17315 | D11: 21509.102 | E11: 17067.306 | F11: 17619.93 | G11: 17815.049

Sheet Tb 5 Tax revenue
A1: Tax Revenue
A2: (millions of dollars)
B3: 2023-24 | C3: 2024-25 | E3: 2025-26 | F3: 2026-27 | G3: 2027-28
B4: Actual | C4: Budget | D4: Forecast | E4: Estimate | F4: Target | G4: Target
A5: Personal income tax | B5: 15160 | C5: 15604 | D5: 16119.993 | E5: 15509.644 | F5: 16270.87 | G5: 16980.97
A6: Corporate income tax | B6: 7044.1 | C6: 7028 | D6: 7350.649 | E6: 6764.266 | F6: 6938.231 | G6: 7253.56
A7: Education property tax | B7: 2526.3 | C7: 2733 | D7: 2731.903 | E7: 3124 | F7: 3435 | G7: 3576
A8: Other taxes | B8: 2016.4 | C8: 3280.418 | D8: 3263.038 | E8: 3439.361 | F8: 3506.478 | G8: 3579.784
A9: Total Tax Revenue | B9: 26746.8 | C9: 28645.418 | D9: 29465.582 | E9: 28837.271 | F9: 30150.579 | G9: 31390.314

Sheet Tb 6 Fed Transfers
A1: Transfers from Government of Canada
A2: (millions of dollars)
B4: 2023-24 | C4: 2024-25 | E4: 2025-26 | F4: 2026-27 | G4: 2027-28
B5: Actual | C5: Budget | D5: Forecast | E5: Estimate | F5: Target | G5: Target
A6: Canada Health Transfer | B6: 5963.7 | C6: 6164 | D6: 6155.708 | E6: 6559.639 | F6: 7033.12 | G6: 7456.213
A7: Canada Social Transfer | B7: 1907.9 | C7: 2001.236 | D7: 1993.078 | E7: 2089.122 | F7: 2197.252 | G7: 2285.062
A8: Transfers to SUCH sector | B8: 608.4 | C8: 633.334 | D8: 668.19 | E8: 692.921 | F8: 704.083 | G8: 714.584
A9: Infrastructure support | B9: 714.8 | C9: 839.981 | D9: 874.549 | E9: 807.483 | F9: 980.839 | G9: 981.384
A10: Agriculture support programs | B10: 615 | C10: 536.659 | D10: 577.656 | E10: 551.928 | F10: 594.675 | G10: 627.894
A11: Labour market agreements | B11: 322 | C11: 321.706 | D11: 257.099 | E11: 257.484 | F11: 257.484 | G11: 257.484
A12: Early learning child care agreements | B12: 880.8 | C12: 1139.2 | D12: 1251.494 | E12: 1146.598 | F12: 1121.024 | G12: 1121.024
A13: Other transfers | B13: 1323.3 | C13: 1003.605 | D13: 1180.465 | E13: 1182.324 | F13: 864.119 | G13: 784.428
A14: Total Federal Transfers | B14: 12335.9 | C14: 12639.721 | D14: 12958.239 | E14: 13287.499 | F14: 13752.596 | G14: 14228.073

Sheet Tb 7 Inv. income
A1: Fund Assets / Investment Income
A2: (millions of dollars)
C3: Investment Income
B4: Assets as at | C4: 2023-24 | D4: 2024-25 | F4: 2025-26 | G4: 2026-27 | H4: 2027-28
B5: Mar. 31, 2024 | C5: Actual | D5: Budget | E5: Forecast | F5: Estimate | G5: Target | H5: Target
A6: Heritage Savings Trust Fund | B6: 20872 | C6: 2064.8 | D6: 1042.032 | E6: 2298.486 | F6: 1128.664 | G6: 1372.986 | H6: 1611.739
A7: Endowment funds a | B7: 4949 | C7: 526.8 | D7: 291.002 | E7: 672.589 | F7: 260.554 | G7: 289.887 | H7: 334.334
A8: Loans to local authorities | B8: 14590 | C8: 801.9 | D8: 757.7 | E8: 725.177 | F8: 576.818 | G8: 592.283 | H8: 626.423
A9: Ag. Financial Services Corp. | B9: 2966 | C9: 92.8 | D9: 148.343 | E9: 153.776 | F9: 148.717 | G9: 155.111 | H9: 165.714
A10: SUCH sector | B10: n.a. | C10: 365 | D10: 431 | E10: 534.019 | F10: 459 | G10: 441 | H10: 448
A11: Other b | B11: 3338 | C11: 729.8 | D11: 596.679 | E11: 787.414 | F11: 308.339 | G11: 283.579 | H11: 281.038
A12: Total Assets / Inv. Income | B12: 46715 | C12: 4581.1 | D12: 3266.756 | E12: 5171.461 | F12: 2882.092 | G12: 3134.846 | H12: 3467.248

Sheet Tb 8 Other sources
A1: Revenue from Other Sources
A2: (millions of dollars)
B4: 2023-24 | C4: 2024-25 | E4: 2025-26 | F4: 2026-27 | G4: 2027-28
B5: Actual | C5: Budget | D5: Forecast | E5: Estimate | F5: Target | G5: Target
A6: AGLC - gaming / lottery | B6: 1568.8 | C6: 1486.88 | D6: 1517.671 | E6: 1539.67 | F6: 1577.262 | G6: 1620.968
A7: AGLC - liquor | B7: 790.6 | C7: 807.7 | D7: 777.928 | E7: 783.42 | F7: 769.75 | G7: 760.918
A8: AGLC - cannabis | B8: 10.8 | C8: 7.2 | D8: 8.711 | E8: 9.038 | F8: 13.532 | G8: 25.404
A9: ATB Financial | B9: 336.8 | C9: 265.946 | D9: 284.834 | E9: 284.949 | F9: 352.6 | G9: 409.596
A10: Balancing Pool | B10: 160 | C10: 64.51 | D10: 61.324 | E10: 57.39 | F10: 53.131 | G10: 56.127
A11: Other Net Income from GBE (APMC/CUDGCo/PSIs) | B11: -1630.3 | C11: -509.319 | D11: -586.086 | E11: -658.731 | F11: -260.456 | G11: -305.502
A12: Post-secondary tuition fees | B12: 1835.5 | C12: 1998.965 | D12: 2153.641 | E12: 2133.312 | F12: 2214.16 | G12: 2260.05
A13: Health / school board fees | B13: 817.6 | C13: 845.392 | D13: 905.571 | E13: 911.582 | F13: 936.743 | G13: 961.411
A14: Other premiums, fees and licences | B14: 2911.8 | C14: 2539.096 | D14: 2505.559 | E14: 2590.846 | F14: 2722.624 | G14: 2810.428
A15: SUCH sales, rentals, services | B15: 1123 | C15: 946.7 | D15: 1024.318 | E15: 1277.036 | F15: 1309.756 | G15: 1374.462
A16: SUCH fundraising, donations, gifts | B16: 788.3 | C16: 783.694 | D16: 848.357 | E16: 821.109 | F16: 865.978 | G16: 881.9
A17: TIER Fund | B17: 907 | C17: 539 | D17: 264.75 | E17: 409 | F17: 271 | G17: 313
... A19: Total Revenue from Other Sources | B19: 11780.8 | C19: 11670.437 | D19: 11587.184 | E19: 12063.613 | F19: 12732.147 | G19: 13068.641

Sheet Tb 9 Sensitivities
A1: Sensitivities to Fiscal Year Assumptions, 2025-26a
A2: (millions of dollars)
B4: Change | C4: Net Impact
A5: Oil price (WTI US$/bbl) | B5: -$1 | C5: -750
A6: Light-heavy oil price differential (US$/bbl) | B6: +$1 | C6: -740
A7: Natural gas price (Cdn$/GJ) | B7: -10¢ | C7: -5
A8: Exchange rate (US¢/Cdn$) | B8: + 1¢ | C8: -560
A9: Interest rates | B9: +1% | C9: -277
A10: Primary household income | B10: -1% | C10: -200

Sheet END

Sheet DELETE - Tb 2 rev changes
A1: Evolution of Revenue Forecast Since Budget 2023
A2: (millions of dollars)
B3: Budget | C3: 2023-24 | D3: Budget | E3: Change fr | F3: Change fr | O3: Budget | P3: 2022-23 | Q3: Budget | R3: Change fr | S3: Change fr
A4: Fiscal Year | B4: 2023 | C4: Mid-year | D4: 2024 | E4: Bud 2023 | F4: Mid-year | N4: Fiscal Year | O4: 2022 | P4: Mid-year | Q4: 2023 | R4: Bud 2022 | S4: Mid-year
A6: 2023-24: | N6: 2022-23:
A7: Personal income tax | B7: 14069 | C7: 15014 | D7: ='Tb 1 Total Revenue'!D5 -> 16119.993 | E7: =D7-B7 -> 2050.993 | F7: =D7-C7 -> 1105.993
A8: Corporate income tax | B8: 5911 | C8: 6800 | D8: ='Tb 1 Total Revenue'!D6 -> 7350.649 | E8: =D8-B8 -> 1439.649 | F8: =D8-C8 -> 550.649 | N8: GBE | O8: 2435 | P8: 2475 | Q8: ='Tb 1 Total Revenue'!D12 -> 2064.382 | R8: =Q8-O8 -> -370.618 | S8: =Q8-P8 -> -410.618
A9: Other taxes | B9: 5012 | C9: 4484 | D9: ='Tb 1 Total Revenue'!D7 -> 5994.941 | E9: =D9-B9 -> 982.941 | F9: =D9-C9 -> 1510.941 | N9: PFL | O9: 4490 | P9: 4756 | Q9: ='Tb 1 Total Revenue'!D13 -> 5564.771 | R9: =Q9-O9 -> 1074.771 | S9: =Q9-P9 -> 808.771
A10: Resource revenue | B10: 18361 | C10: 19667 | D10: ='Tb 1 Total Revenue'!D8+'Tb 1 Total Revenue'!D9 -> 21509.102 | E10: =D10-B10 -> 3148.102 | F10: =D10-C10 -> 1842.102 | N10: Other | O10: 3581 | P10: 3693 | Q10: ='Tb 1 Total Revenue'!D14 -> 3958.031 | R10: =Q10-O10 -> 377.031 | S10: =Q10-P10 -> 265.031
A11: Federal govt. transfers | B11: 12552 | C11: 12738 | D11: ='Tb 1 Total Revenue'!D10 -> 12958.239 | E11: =D11-B11 -> 406.239 | F11: =D11-C11 -> 220.239 | N11: 2022-23 revenue fr. other sources | O11: =SUM(O8:O10) -> 10506 | P11: =SUM(P8:P10) -> 10924 | Q11: =SUM(Q8:Q10) -> 11587.184 | R11: =SUM(R8:R10) -> 1081.184 | S11: =SUM(S8:S10) -> 663.184
A12: Investment income | B12: 3154 | C12: 3855 | D12: ='Tb 1 Total Revenue'!D11 -> 5171.461 | E12: =D12-B12 -> 2017.461 | F12: =D12-C12 -> 1316.461
A13: Revenue fr. other sources | B13: 11594 | C13: =2472+5049+4226 -> 11747 | D13: ='Tb 1 Total Revenue'!D14+'Tb 1 Total Revenue'!D12+'Tb 1 Total Revenue'!D13 -> 11587.184 | E13: =D13-B13 -> -6.816 | F13: =D13-C13 -> -159.816 | N13: 2023-24:
A14: Total 2022-23 revenue | B14: =SUM(B7:B13) -> 70653 | C14: =SUM(C7:C13) -> 74305 | D14: =SUM(D7:D13) -> 80691.569 | E14: =SUM(E7:E13) -> 10038.569 | F14: =SUM(F7:F13) -> 6386.569 | H14: =D14-B14 -> 10038.569 | I14: =D14-C14 -> 6386.569 | N14: Revenue fr. other sources
R15: =Q15-O15 -> 0 | S15: =Q15-P15 -> 0
A16: 2024-25: | N16: GBE | O16: 2630 | P16: 2657 | Q16: ='Tb 1 Total Revenue'!E12 -> 2015.736 | R16: =Q16-O16 -> -614.264 | S16: =Q16-P16 -> -641.264
A17: Personal income tax | B17: 15034 | C17: 15405 | D17: ='Tb 1 Total Revenue'!E5 -> 15509.644 | E17: =D17-B17 -> 475.644 | F17: =D17-C17 -> 104.644 | N17: PFL | O17: 4606 | P17: 4734 | Q17: ='Tb 1 Total Revenue'!E13 -> 5635.74 | R17: =Q17-O17 -> 1029.74 | S17: =Q17-P17 -> 901.74
A18: Corporate income tax | B18: 6254 | C18: 6894 | D18: ='Tb 1 Total Revenue'!E6 -> 6764.266 | E18: =D18-B18 -> 510.266 | F18: =D18-C18 -> -129.734 | J18: CIT | K18: =E8+E18+E28 -> 2298.146 | N18: Other | O18: 3700 | P18: 3675 | Q18: ='Tb 1 Total Revenue'!E14 -> 4412.137 | R18: =Q18-O18 -> 712.137 | S18: =Q18-P18 -> 737.137
A19: Other taxes | B19: 5767 | C19: 5798 | D19: ='Tb 1 Total Revenue'!E7 -> 6563.361 | E19: =D19-B19 -> 796.361 | F19: =D19-C19 -> 765.361 | J19: NRR | K19: =E10+E20+E30 -> 4809.338 | N19: 2023-24 revenue fr. other sources | O19: =SUM(O16:O18) -> 10936 | P19: =SUM(P16:P18) -> 11066 | Q19: =SUM(Q16:Q18) -> 12063.613 | R19: =SUM(R16:R18) -> 1127.613 | S19: =SUM(S16:S18) -> 997.613
A20: Resource revenue | B20: 17284 | C20: 17553 | D20: ='Tb 1 Total Revenue'!E8+'Tb 1 Total Revenue'!E9 -> 17067.306 | E20: =D20-B20 -> -216.694 | F20: =D20-C20 -> -485.694 | K20: =SUM(K18:K19) -> 7107.484 | L20: =K20/K21 -> 0.41242379
A21: Federal govt. transfers | B21: 12475 | C21: 12731 | D21: ='Tb 1 Total Revenue'!E10 -> 13287.499 | E21: =D21-B21 -> 812.499 | F21: =D21-C21 -> 556.499 | K21: =E14+E24+E34 -> 17233.448 | N21: 2024-25:
A22: Investment income | B22: 3273 | C22: 3405 | D22: ='Tb 1 Total Revenue'!E11 -> 2882.092 | E22: =D22-B22 -> -390.908 | F22: =D22-C22 -> -522.908 | N22: Revenue fr. other sources
A23: Revenue fr. other sources | B23: 11637 | C23: =2161+5277+3933 -> 11371 | D23: ='Tb 1 Total Revenue'!E12+'Tb 1 Total Revenue'!E13+'Tb 1 Total Revenue'!E14 -> 12063.613 | E23: =D23-B23 -> 426.613 | F23: =D23-C23 -> 692.613 | N23: GBE | O23: 2656 | P23: 2422 | Q23: ='Tb 1 Total Revenue'!F12 -> 2505.819 | R23: =Q23-O23 -> -150.181 | S23: =Q23-P23 -> 83.819
A24: Total 2023-24 revenue | B24: =SUM(B17:B23) -> 71724 | C24: =SUM(C17:C23) -> 73157 | D24: =SUM(D17:D23) -> 74137.781 | E24: =SUM(E17:E23) -> 2413.781 | F24: =SUM(F17:F23) -> 980.781 | H24: =D24-B24 -> 2413.781 | I24: =D24-C24 -> 980.781 | N24: PFL | O24: 4736 | P24: 4920 | Q24: ='Tb 1 Total Revenue'!F13 -> 5873.527 | R24: =Q24-O24 -> 1137.527 | S24: =Q24-P24 -> 953.527
R25: =Q25-O25 -> 0 | S25: =Q25-P25 -> 0
A26: 2025-26: | N26: Other | O26: 3685 | P26: 3782 | Q26: ='Tb 1 Total Revenue'!F14 -> 4352.801 | R26: =Q26-O26 -> 667.801 | S26: =Q26-P26 -> 570.801
A27: Personal income tax | B27: 16071 | C27: 16483 | D27: ='Tb 1 Total Revenue'!F5 -> 16270.87 | E27: =D27-B27 -> 199.87 | F27: =D27-C27 -> -212.13 | N27: Total 2024-25 revenue fr. other sources | O27: =SUM(O23:O26) -> 11077 | P27: =SUM(P23:P26) -> 11124 | Q27: =SUM(Q23:Q26) -> 12732.147 | R27: =SUM(R23:R26) -> 1655.147 | S27: =SUM(S23:S26) -> 1608.147
A28: Corporate income tax | B28: 6590 | C28: 7103 | D28: ='Tb 1 Total Revenue'!F6 -> 6938.231 | E28: =D28-B28 -> 348.231 | F28: =D28-C28 -> -164.769
A29: Other taxes | B29: 5948 | C29: 6000 | D29: ='Tb 1 Total Revenue'!F7 -> 6941.478 | E29: =D29-B29 -> 993.478 | F29: =D29-C29 -> 941.478
A30: Resource revenue | B30: 15742 | C30: 17383 | D30: ='Tb 1 Total Revenue'!F8+'Tb 1 Total Revenue'!F9 -> 17619.93 | E30: =D30-B30 -> 1877.93 | F30: =D30-C30 -> 236.93
A31: Federal govt. transfers | B31: 13113 | C31: 13220 | D31: ='Tb 1 Total Revenue'!F10 -> 13752.596 | E31: =D31-B31 -> 639.596 | F31: =D31-C31 -> 532.596
A32: Investment income | B32: 3407 | C32: 3505 | D32: ='Tb 1 Total Revenue'!F11 -> 3134.846 | E32: =D32-B32 -> -272.154 | F32: =D32-C32 -> -370.154
A33: Revenue fr. other sources | B33: =2647+5360+3730 -> 11737 | C33: =2274+5352+3636 -> 11262 | D33: ='Tb 1 Total Revenue'!F12+'Tb 1 Total Revenue'!F13+'Tb 1 Total Revenue'!F14 -> 12732.147 | E33: =D33-B33 -> 995.147 | F33: =D33-C33 -> 1470.147
A34: Total 2024-25 revenue | B34: =SUM(B27:B33) -> 72608 | C34: =SUM(C27:C33) -> 74956 | D34: =SUM(D27:D33) -> 77390.098 | E34: =SUM(E27:E33)-1 -> 4781.098 | F34: =SUM(F27:F33) -> 2434.098 | H34: =D34-B34 -> 4782.098 | I34: =D34-C34 -> 2434.098
E38: =E34+E24+E14 -> 17233.448
A42: pdf named: B24-FP_Rev_tb02_rctq.pdf
